lime_stability/__init__.py
lime_stability/stability.py
lime_stability/tests.py
lime_stability/utils.py
lime_stability-0.1.1.dist-info/LICENSE
lime_stability-0.1.1.dist-info/METADATA
lime_stability-0.1.1.dist-info/WHEEL
lime_stability-0.1.1.dist-info/top_level.txt
lime_stability-0.1.1.dist-info/RECORD
