Metadata-Version: 2.1
Name: lime-stability
Version: 0.1.1
Summary: A package to evaluate Lime stability
Home-page: https://github.com/giorgiovisani/lime_stability.git
Author: Giorgio Visani
Author-email: giorgio.visani2@unibo.it
License: BSD
Platform: UNKNOWN
Requires-Dist: lime
Requires-Dist: statsmodels
Requires-Dist: statistics
Requires-Dist: numpy
Requires-Dist: scikit-learn (>=0.18)
